edc_next_appointment/__init__.py
edc_next_appointment/apps.py
edc_next_appointment/choices.py
edc_next_appointment/list_data.py
edc_next_appointment/model_mixins.py
edc_next_appointment/modeladmin_mixins.py
edc_next_appointment/modelform_mixins.py
edc_next_appointment/urls.py
edc_next_appointment/form_validators/__init__.py
edc_next_appointment/form_validators/form_validator_mixins.py
edc_next_appointment/form_validators/next_appointment_form_validator.py
edc_next_appointment/migrations/0001_initial.py
edc_next_appointment/migrations/0002_infosources_extra_value.py
edc_next_appointment/migrations/0003_remove_infosources_edc_next_ap_id_0fdae6_idx_and_more.py
edc_next_appointment/migrations/0004_alter_infosources_display_index_and_more.py
edc_next_appointment/migrations/0005_alter_infosources_name_and_more.py
edc_next_appointment/migrations/0006_alter_infosources_options.py
edc_next_appointment/migrations/0007_remove_infosources_edc_next_ap_name_543d65_idx.py
edc_next_appointment/migrations/__init__.py
edc_next_appointment/models/__init__.py
edc_next_appointment/models/list_models.py
edc_next_appointment/tests/__init__.py
edc_next_appointment/tests/holidays.csv
edc_next_appointment/tests/etc/user-aes-local.key
edc_next_appointment/tests/etc/user-aes-restricted.key
edc_next_appointment/tests/etc/user-rsa-local-private.pem
edc_next_appointment/tests/etc/user-rsa-local-public.pem
edc_next_appointment/tests/etc/user-rsa-restricted-private.pem
edc_next_appointment/tests/etc/user-rsa-restricted-public.pem
edc_next_appointment/tests/etc/user-salt-local.key
edc_next_appointment/tests/etc/user-salt-restricted.key
edc_next_appointment/tests/tests/__init__.py
edc_next_appointment/tests/tests/test_next_appointment.py
next_appointment_app/__init__.py
next_appointment_app/admin.py
next_appointment_app/admin_site.py
next_appointment_app/apps.py
next_appointment_app/consents.py
next_appointment_app/forms.py
next_appointment_app/models.py
next_appointment_app/navbars.py
edc_next_appointment-0.3.1.dist-info/AUTHORS
edc_next_appointment-0.3.1.dist-info/LICENSE
edc_next_appointment-0.3.1.dist-info/METADATA
edc_next_appointment-0.3.1.dist-info/WHEEL
edc_next_appointment-0.3.1.dist-info/top_level.txt
edc_next_appointment-0.3.1.dist-info/RECORD
