Metadata-Version: 2.1
Name: edc-next-appointment
Version: 0.3.1
Summary: Base classes for managing next appointment CRF at each timepoint in clinicedc/edc projects
Home-page: https://github.com/clinicedc/edc-next-appointment
Author: Erik van Widenfelt
Author-email: ew2789@gmail.com
License: GPL license, see LICENSE
Keywords: django Edc appointment,scheduling,CRF,clinicedc,clinical trials
Classifier: Environment :: Web Environment
Classifier: Framework :: Django
Classifier: Framework :: Django :: 4.2
Classifier: Intended Audience :: Developers
Classifier: Intended Audience :: Science/Research
Classifier: Operating System :: OS Independent
Classifier: Programming Language :: Python :: 3.11
Classifier: License :: OSI Approved :: GNU General Public License v3 (GPLv3)
Requires-Python: >=3.11
License-File: LICENSE
License-File: AUTHORS
